{
  "schemaVersion": "1.0.0",
  "projectStateVersion": 3,
  "summary": "New project",
  "architectural_notes": [],
  "known_issues": [
    "Reported bug: 'Call Now/Call Us' button phone number did not update to the provided number."
  ],
  "isFixRequest": true,
  "existing_features": [
    {
      "id": "feature-update-the-site-wide-phone-number-used-for-all-tel-links-so-the-call-now-call-us-button-dials-918824495515",
      "title": "Update the site-wide phone number used for all tel: links so the Call Now/Call Us button dials +918824495515.",
      "reqIds": [
        "REQ-1"
      ],
      "version": 1
    }
  ],
  "new_feature_requests": [
    {
      "id": "AR-2",
      "summary": "Ensure every phone/call CTA in the UI uses the centralized contactConfig.phoneUrl (no hard-coded phone numbers) so future phone updates work consistently.",
      "reqIds": [
        "REQ-2"
      ],
      "status": "pending"
    },
    {
      "id": "AR-3",
      "summary": "Add/refresh a post-deploy smoke-check item to verify the Call Now/Call Us button dials the configured number (+918824495515) on mobile.",
      "reqIds": [
        "REQ-3"
      ],
      "status": "pending"
    }
  ],
  "projectName": "Fix Call Now/Call Us phone number to use provided number",
  "clarification_mode": "instant",
  "clarification_rounds": 0
}